altcorp/__init__.py
altcorp/admin.py
altcorp/app_settings.py
altcorp/apps.py
altcorp/auth_hooks.py
altcorp/helpers.py
altcorp/models.py
altcorp/tasks.py
altcorp/urls.py
altcorp/migrations/0001_initial.py
altcorp/migrations/0002_alter_general_options.py
altcorp/migrations/__init__.py
altcorp/static/altcorp/css/create_requests.css
altcorp/static/altcorp/css/global.css
altcorp/static/altcorp/css/manage.css
altcorp/static/altcorp/img/Spinner-1s-64px-dark.gif
altcorp/static/altcorp/img/Spinner-1s-64px-light.gif
altcorp/static/altcorp/js/vendor/htmx/htmx.min.js
altcorp/templates/altcorp/base.html
altcorp/templates/altcorp/create_requests.html
altcorp/templates/altcorp/manage_requests.html
altcorp/templates/altcorp/bundles/helper-js.html
altcorp/templates/altcorp/bundles/htmx.html
altcorp/templates/altcorp/partials/manage_empty_row.html
altcorp/templates/altcorp/partials/request_corporations.html
altcorp/templates/altcorp/partials/requests_list.html
altcorp/templates/altcorp/partials/revocations_list.html
altcorp/templates/altcorp/partials/spinner.html
altcorp/templates/altcorp/partials/standing_symbol.html
altcorp/templates/altcorp/partials/tbl_effective_requests.html
altcorp/templates/altcorp/partials/navigation/top-navigation.html
altcorp/tests/__init__.py
altcorp/tests/test_tasks.py
altcorp/views/common.py
altcorp/views/create_requests.py
altcorp/views/manage_requests.py
aa_altcorp-1.1.1.dist-info/licenses/LICENSE
aa_altcorp-1.1.1.dist-info/WHEEL
aa_altcorp-1.1.1.dist-info/METADATA
aa_altcorp-1.1.1.dist-info/RECORD
