Metadata-Version: 2.4
Name: aa-altcorp
Version: 1.1.1
Summary: Example plugin app for Alliance Auth.
Author-email: "Swashman(John Nelson)" <jnelson2288@gmail.com>
Requires-Python: >=3.9
Classifier: Environment :: Web Environment
Classifier: Framework :: Django
Classifier: Framework :: Django :: 4.0
Classifier: Framework :: Django :: 4.2
Classifier: Intended Audience :: Developers
Classifier: License :: OSI Approved :: MIT License
Classifier: Operating System :: OS Independent
Classifier: Programming Language :: Python
Classifier: Programming Language :: Python :: 3 :: Only
Classifier: Programming Language :: Python :: 3.9
Classifier: Programming Language :: Python :: 3.10
Classifier: Programming Language :: Python :: 3.11
Classifier: Programming Language :: Python :: 3.12
Classifier: Programming Language :: Python :: 3.13
Classifier: Topic :: Internet :: WWW/HTTP
Classifier: Topic :: Internet :: WWW/HTTP :: Dynamic Content
License-File: LICENSE
Requires-Dist: allianceauth>=4
Requires-Dist: allianceauth-app-utils>=1.18
Requires-Dist: dhooks-lite>=1
Requires-Dist: py-cord>2,<3
Project-URL: Changelog, https://github.com/astrum-mechanica/aa-altcorp/blob/master/CHANGELOG.md
Project-URL: Documentation, https://github.com/astrum-mechanica/aa-altcorp/blob/master/README.md
Project-URL: Homepage, https://github.com/astrum-mechanica/aa-altcorp
Project-URL: Source, https://github.com/astrum-mechanica/aa-altcorp
Project-URL: Tracker, https://github.com/astrum-mechanica/aa-altcorp/issues
